__init__.py
admm_fit.py
config.py
cvae.py
cvaeglrm.py
hyper_parameter_optimization.py
imputation.py
local_fit_numba.py
model_fit.py
parse_opt.py
preprocess.py
run_model.py
utils.py
cvae_glrm-1.0.5.dist-info/METADATA
cvae_glrm-1.0.5.dist-info/WHEEL
cvae_glrm-1.0.5.dist-info/entry_points.txt
cvae_glrm-1.0.5.dist-info/top_level.txt
cvae_glrm-1.0.5.dist-info/RECORD
