Metadata-Version: 2.1
Name: cvae-glrm
Version: 1.0.5
Summary: Conditional Variational AutoEncoder - Graph Laplacian Regularized Model
Home-page: https://az7jh2.github.io/CVAE-GLRM/
Author: Ningshan Li
Author-email: hill103.2@gmail.com
Project-URL: Documentation, https://cvae-glrm.readthedocs.io/en/latest/
Project-URL: Source, https://github.com/az7jh2/CVAE-GLRM
Classifier: Development Status :: 5 - Production/Stable
Classifier: License :: OSI Approved :: MIT License
Classifier: Programming Language :: Python :: 3.9
Classifier: Operating System :: OS Independent
Requires-Python: >=3.9.12
Requires-Dist: numpy (==1.22.4)
Requires-Dist: scipy (==1.8.1)
Requires-Dist: pandas (==1.4.3)
Requires-Dist: networkx (==2.8.4)
Requires-Dist: matplotlib (==3.5.2)
Requires-Dist: scikit-learn (==1.1.1)
Requires-Dist: numba (==0.55.2)
Requires-Dist: openpyxl (==3.0.10)
Requires-Dist: tensorflow (==2.9.1)
Requires-Dist: scanpy (==1.9.1)
Requires-Dist: scikit-misc (==0.1.4)
Requires-Dist: seaborn (==0.11.2)
Requires-Dist: umap-learn (==0.5.3)
Requires-Dist: distinctipy (==1.2.2)
Requires-Dist: reportlab (==3.6.12)
